Workbook
Name CIQWBGuid: "e778162b-a8f3-4f2e-935f-34d73fb7e972"
Name CIQWBGuid: "eeeac8b3-2cb4-40c8-a5e7-67bd1e29d27d"
Name CIQWBInfo: "{ ""CIQVersion"":""9.51.3510.3078"" }"
Name CurrentPrice: Cover!$G$19
Name Gross_Profit: '[1]Advanced Financial Analysis'!$9:$9
Name IFF_Price: Cover!$G$19
Name IQ_CH: 110000
Name IQ_CQ: 5000
Name IQ_CY: 10000
Name IQ_DAILY: 500000
Name IQ_DNTM: 700000
Name IQ_FH: 100000
Name IQ_FQ: 500
Name IQ_FWD_CY: 10001
Name IQ_FWD_CY1: 10002
Name IQ_FWD_CY2: 10003
Name IQ_FWD_FY: 1001
Name IQ_FWD_FY1: 1002
Name IQ_FWD_FY2: 1003
Name IQ_FWD_Q: 501
Name IQ_FWD_Q1: 502
Name IQ_FWD_Q2: 503
Name IQ_FY: 1000
Name IQ_LATESTK: 1000
Name IQ_LATESTQ: 500
Name IQ_LTM: 2000
Name IQ_LTMMONTH: 120000
Name IQ_MONTH: 15000
Name IQ_MTD: 800000
Name IQ_NAMES_REVISION_DATE_: 45318.8008796296
Name IQ_NTM: 6000
Name IQ_QTD: 750000
Name IQ_TODAY: 0
Name IQ_WEEK: 50000
Name IQ_YTD: 3000
Name IQ_YTDMONTH: 130000
Name Sensitivity: '[1]Advanced Financial Analysis'!$D$49
Name SG_A: '[1]Advanced Financial Analysis'!$11:$11
Name TargetCurrentPrice: Comps!$E$18
Name TargetDilutedShares: Comps!$F$18

Sheet Cover
A1: eb
D11: FSLR - CamSIF Michaelmas
D13: Industrials
D14: CamSIF
D17: Date | G17: =+TODAY() -> 45982
D19: Share Price | E19: 45976 | G19: 245.84
L20: Case Legend
D21: OpCase | G21: 3 | J21: 1 | L21: 1 | M21: Base
J22: 2 | L22: =L21+1 -> 2 | M22: Bull
D23: Case Upside | F23: =DCF!V25 -> 148.4385 | G23: =(DCF!V25-CurrentPrice)/CurrentPrice -> -0.39619875 | J23: 3 | L23: =L22+1 -> 3 | M23: Bear
D25: Base Case | G25: 359.12
D27: Base Upside | G27: =(G25-CurrentPrice)/CurrentPrice -> 0.4607875

Sheet Assumptions
C2: First Solar
C3: Assumptions
C4: Active Case: | D4: 3
C6: $ In Millions, Unless Otherwise Noted
F7: Historical Years | I7: Forecasted Years | P7: Comments
F8: 2021A | G8: 2022A | H8: 2023A | I8: 2024A | J8: 2025E | K8: 2026E | L8: 2027E | M8: 2028E
C10: Products Revenue | F10: ='Three Statement Model'!D32 -> 2932.4 | G10: ='Three Statement Model'!E32 -> 2619.3 | H10: ='Three Statement Model'!F32 -> 3318.6 | I10: =4206.3 -> 4206.3 | J10: =J13*J19 -> 5467.878 | K10: =K13*K19 -> 7108.2414 | L10: =L13*L19 -> 9240.7138 | M10: =M13*M19 -> 12012.928
C11: % Growth | G11: =(G10-F10)/F10 -> -0.10677261 | H11: =(H10-G10)/G10 -> 0.26697973 | I11: =(I10-H10)/H10 -> 0.26749232 | J11: =(J10-I10)/I10 -> 0.29992583 | K11: =(K10-J10)/J10 -> 0.3 | L11: =(L10-K10)/K10 -> 0.3 | M11: =(M10-L10)/L10 -> 0.3
C13: Modules Sold Per year | F13: 7900 | G13: 9100 | H13: 12100 | I13: =15578 -> 15578 | J13: =+I13*(1+J14) -> 20251.4 | K13: =+J13*(1+K14) -> 26326.82 | L13: =+K13*(1+L14) -> 34224.866 | M13: =+L13*(1+M14) -> 44492.326
C14: % Growth | G14: =(G13/F13)-1 -> 0.15189873 | H14: =(H13/G13)-1 -> 0.32967033 | I14: =(I13/H13)-1 -> 0.28743802 | J14: =+OFFSET(J14,$D$4,) -> 0.3 | K14: =+OFFSET(K14,$D$4,) -> 0.3 | L14: =+OFFSET(L14,$D$4,) -> 0.3 | M14: =+OFFSET(M14,$D$4,) -> 0.3
C15: Base | J15: 0.35 | K15: 0.35 | L15: 0.35 | M15: 0.35
C16: Bull | J16: 0.38 | K16: 0.38 | L16: 0.38 | M16: 0.38
C17: Bear | J17: 0.3 | K17: 0.3 | L17: 0.3 | M17: 0.3
P18: Modules sold per year is based on the GW figures in the 10-Q. E.g. 2024A was 23.6GW of solar modules. Revenue per model sold is the Revenue/Gwatt. Per module on ASP
C19: Revenue Per Module Sold | F19: =F10/F13 -> 0.37118987 | G19: =G10/G13 -> 0.28783516 | H19: =H10/H13 -> 0.27426446 | I19: =I10/I13 -> 0.27001541 | J19: =J20 -> 0.27 | K19: =K20 -> 0.27 | L19: =L20 -> 0.27 | M19: =M20 -> 0.27
C20: % Growth | G20: =(G19-F19)/F19 -> -0.22456084 | H20: =(H19-G19)/G19 -> -0.047147478 | J20: =+OFFSET(J20,$D$4,) -> 0.27 | K20: =+OFFSET(K20,$D$4,) -> 0.27 | L20: =+OFFSET(L20,$D$4,) -> 0.27 | M20: =+OFFSET(M20,$D$4,) -> 0.27
C21: Base | J21: 0.3 | K21: 0.3 | L21: 0.3 | M21: 0.3
C22: Bull | J22: 0.32 | K22: 0.3 | L22: 0.3 | M22: 0.3
C23: Bear | J23: 0.27 | K23: 0.27 | L23: 0.27 | M23: 0.27
C25: Cost of Goods Sold | F25: 2193.4 | G25: 2491.7 | H25: 2017.9 | I25: =I10*(I26) -> 1880.37 | J25: =J10*(J26) -> 3280.7268 | K25: =K10*(K26) -> 4264.9448 | L25: =L10*(L26) -> 5544.4283 | M25: =M10*(M26) -> 7207.7568
C26: % of Products Revenue | F26: =F25/F10 -> 0.747988 | G26: =G25/G10 -> 0.95128469 | H26: =H25/H10 -> 0.60805761 | I26: ='Three Statement Model'!G33/'Three Statement Model'!G32*-1 -> 0.44703659 | J26: =+OFFSET(J26,$D$4,) -> 0.6 | K26: =+OFFSET(K26,$D$4,) -> 0.6 | L26: =+OFFSET(L26,$D$4,) -> 0.6 | M26: =+OFFSET(M26,$D$4,) -> 0.6
C27: Base | J27: 0.5 | K27: 0.5 | L27: 0.5 | M27: 0.5
C28: Bull | J28: 0.5 | K28: 0.5 | L28: 0.48 | M28: 0.45
C29: Bear | J29: 0.6 | K29: 0.6 | L29: 0.6 | M29: 0.6
C31: SG&A Expense | I31: =I32*(I10) -> 378.567 | J31: =J32*(J10) -> 492.10902 | K31: =K32*(K10) -> 639.74173 | L31: =L32*(L10) -> 831.66424 | M31: =M32*(M10) -> 1081.1635
C32: % of Revenue | F32: =F31/(F19+F10) -> 0 | G32: =G31/(G19+G10) -> 0 | H32: =H31/(H19+H10) -> 0 | I32: =+OFFSET(I32,$D$4,) -> 0.09 | J32: =+OFFSET(J32,$D$4,) -> 0.09 | K32: =+OFFSET(K32,$D$4,) -> 0.09 | L32: =+OFFSET(L32,$D$4,) -> 0.09 | M32: =+OFFSET(M32,$D$4,) -> 0.09
C33: Base | I33: 0.07 | J33: 0.07 | K33: 0.07 | L33: 0.07 | M33: 0.07
C34: Bull | I34: 0.06 | J34: 0.06 | K34: 0.06 | L34: 0.06 | M34: 0.06
C35: Bear | I35: 0.09 | J35: 0.09 | K35: 0.09 | L35: 0.09 | M35: 0.09
C37: R&D Expense | I37: =I38*(I10) -> 164.0457 | J37: =J38*(J10) -> 213.24724 | K37: =K38*(K10) -> 277.22141 | L37: =L38*(L10) -> 360.38784 | M37: =M38*(M10) -> 468.50419
C38: % of Revenue | F38: =F37/(F19+F10) -> 0 | G38: =G37/(G19+G10) -> 0 | H38: =H37/(H19+H10) -> 0 | I38: =+OFFSET(I38,$D$4,) -> 0.039 | J38: =+OFFSET(J38,$D$4,) -> 0.039 | K38: =+OFFSET(K38,$D$4,) -> 0.039 | L38: =+OFFSET(L38,$D$4,) -> 0.039 | M38: =+OFFSET(M38,$D$4,) -> 0.039
C39: Base | I39: 0.035 | J39: 0.035 | K39: 0.035 | L39: 0.035 | M39: 0.035
C40: Bull | I40: 0.035 | J40: 0.035 | K40: 0.035 | L40: 0.035 | M40: 0.035
C41: Bear | I41: 0.039 | J41: 0.039 | K41: 0.039 | L41: 0.039 | M41: 0.039
C43: Depreciation & Amort | F43: 243.6 | G43: 253.3 | H43: 292 | I43: =I44*I10 -> 504.756 | J43: =J44*J10 -> 656.14536 | K43: =K44*K10 -> 852.98897 | L43: =L44*L10 -> 1108.8857 | M43: =M44*M10 -> 1441.5514
C44: % of Revenue | G44: =G43/(G19+G10) -> 0.096694601 | H44: =H43/(H19+H10) -> 0.08798164 | I44: =+OFFSET(I44,$D$4,) -> 0.12 | J44: =+OFFSET(J44,$D$4,) -> 0.12 | K44: =+OFFSET(K44,$D$4,) -> 0.12 | L44: =+OFFSET(L44,$D$4,) -> 0.12 | M44: =+OFFSET(M44,$D$4,) -> 0.12
C45: Base | I45: 0.08 | J45: 0.08 | K45: 0.08 | L45: 0.08 | M45: 0.08
C46: Bull | I46: 0.06 | J46: 0.06 | K46: 0.06 | L46: 0.06 | M46: 0.06
C47: Bear | I47: 0.12 | J47: 0.12 | K47: 0.12 | L47: 0.12 | M47: 0.12
C49: Other Operating Expense | I49: =I50*I10 -> 84.126 | J49: =J50*J10 -> 109.35756 | K49: =K50*K10 -> 142.16483 | L49: =L50*L10 -> 184.81428 | M49: =M50*M10 -> 240.25856
C50: % of Revenue | F50: =F49/(F19+F10) -> 0 | G50: =G49/(G19+G10) -> 0 | H50: =H49/(H19+H10) -> 0 | I50: =+OFFSET(I50,$D$4,) -> 0.02 | J50: =+OFFSET(J50,$D$4,) -> 0.02 | K50: =+OFFSET(K50,$D$4,) -> 0.02 | L50: =+OFFSET(L50,$D$4,) -> 0.02 | M50: =+OFFSET(M50,$D$4,) -> 0.02
C51: Base | I51: 0.01 | J51: 0.01 | K51: 0.01 | L51: 0.01 | M51: 0.01
C52: Bull | I52: 0.005 | J52: 0.005 | K52: 0.005 | L52: 0.005 | M52: 0.005
C53: Bear | I53: 0.02 | J53: 0.02 | K53: 0.02 | L53: 0.02 | M53: 0.02
C55: Other Non-Operating Inc. | I55: =I56*I10 -> -84.126 | J55: =J56*J10 -> -109.35756 | K55: =K56*K10 -> -142.16483 | L55: =L56*L10 -> -184.81428 | M55: =M56*M10 -> -240.25856
C56: % of Revenue | F56: =F55/(F10+F19) -> 0 | G56: =G55/(G10+G19) -> 0 | H56: =H55/(H10+H19) -> 0 | I56: =+OFFSET(I56,$D$4,) -> -0.02 | J56: =+OFFSET(J56,$D$4,) -> -0.02 | K56: =+OFFSET(K56,$D$4,) -> -0.02 | L56: =+OFFSET(L56,$D$4,) -> -0.02 | M56: =+OFFSET(M56,$D$4,) -> -0.02
C57: Base | I57: 0.01 | J57: 0.01 | K57: 0.01 | L57: 0.01 | M57: 0.01
C58: Bull | I58: 0.02 | J58: 0.02 | K58: 0.02 | L58: 0.02 | M58: 0.02
C59: Bear | I59: -0.02 | J59: -0.02 | K59: -0.02 | L59: -0.02 | M59: -0.02
C61: Accounts Receivable | I61: =(I62*I31/365) -> 57.044342 | J61: =(J62*J31/365) -> 74.153414 | K61: =(K62*K31/365) -> 96.399438 | L61: =(L62*L31/365) -> 125.31927 | M61: =(M62*M31/365) -> 162.91505
C62: Accounts Receivable Days | F62: =+(F61/(F10+F19))*365 -> 0 | G62: =+(G61/(G10+G19))*365 -> 0 | H62: =+(H61/(H10+H19))*365 -> 0 | I62: =+OFFSET(I62,$D$4,) -> 55 | J62: =+OFFSET(J62,$D$4,) -> 55 | K62: =+OFFSET(K62,$D$4,) -> 55 | L62: =+OFFSET(L62,$D$4,) -> 55 | M62: =+OFFSET(M62,$D$4,) -> 55
C63: Base | I63: 45 | J63: 45 | K63: 45 | L63: 45 | M63: 45
C64: Bull | I64: 35 | J64: 35 | K64: 35 | L64: 35 | M64: 35
C65: Bear | I65: 55 | J65: 55 | K65: 55 | L65: 55 | M65: 55
C67: Other Current Assets | I67: =I10*I68 -> 168.252 | J67: =J10*J68 -> 218.71512 | K67: =K10*K68 -> 284.32966 | L67: =L10*L68 -> 369.62855 | M67: =M10*M68 -> 480.51712
C68: % of Revenue | F68: =F67/(F10+F19) -> 0 | G68: =G67/(G10+G19) -> 0 | H68: =H67/(H10+H19) -> 0 | I68: =+OFFSET(I68,$D$4,) -> 0.04 | J68: =+OFFSET(J68,$D$4,) -> 0.04 | K68: =+OFFSET(K68,$D$4,) -> 0.04 | L68: =+OFFSET(L68,$D$4,) -> 0.04 | M68: =+OFFSET(M68,$D$4,) -> 0.04
C69: Base | I69: 0.025 | J69: 0.025 | K69: 0.025 | L69: 0.025 | M69: 0.025
C70: Bull | I70: 0.015 | J70: 0.015 | K70: 0.015 | L70: 0.015 | M70: 0.015
C71: Bear | I71: 0.04 | J71: 0.04 | K71: 0.04 | L71: 0.04 | M71: 0.04
C73: Long-Term Investments | I73: =(I10*I74) -> 105.1575 | J73: =(J10*J74) -> 136.69695 | K73: =(K10*K74) -> 177.70604 | L73: =(L10*L74) -> 231.01785 | M73: =(M10*M74) -> 300.3232
C74: % of Revenue | F74: =F73/(F19+F25) -> 0 | G74: =G73/(G19+G25) -> 0 | H74: =H73/(H19+H25) -> 0 | I74: =+OFFSET(I74,$D$4,) -> 0.025 | J74: =+OFFSET(J74,$D$4,) -> 0.025 | K74: =+OFFSET(K74,$D$4,) -> 0.025 | L74: =+OFFSET(L74,$D$4,) -> 0.025 | M74: =+OFFSET(M74,$D$4,) -> 0.025
C75: Base | I75: 0.075 | J75: 0.075 | K75: 0.075 | L75: 0.075 | M75: 0.075
C76: Bull | I76: 0.125 | J76: 0.125 | K76: 0.125 | L76: 0.125 | M76: 0.125
C77: Bear | I77: 0.025 | J77: 0.025 | K77: 0.025 | L77: 0.025 | M77: 0.025
C79: Accounts Payable | J79: =J80*J31/365 -> 47.188536 | K79: =K80*K31/365 -> 61.345097 | L79: =L80*L31/365 -> 79.748626 | M79: =M80*M31/365 -> 103.67321
C80: Accounts Payable Days | F80: 27.4 | G80: 27.4 | H80: 27.4 | I80: =+OFFSET(I80,$D$4,) -> 35 | J80: =+OFFSET(J80,$D$4,) -> 35 | K80: =+OFFSET(K80,$D$4,) -> 35 | L80: =+OFFSET(L80,$D$4,) -> 35 | M80: =+OFFSET(M80,$D$4,) -> 35
C81: Base | I81: 45 | J81: 45 | K81: 45 | L81: 45 | M81: 45
C82: Bull | I82: 55 | J82: 55 | K82: 55 | L82: 55 | M82: 55
C83: Bear | I83: 35 | J83: 35 | K83: 35 | L83: 35 | M83: 35
C85: Capital Expenditures | F85: 540.3 | G85: 903.6 | H85: 1386.8 | I85: =I10*I86 -> 1526 | J85: =J10*J86 -> 1531.0058 | K85: =K10*K86 -> 1421.6483 | L85: =L10*L86 -> 1386.1071 | M85: =M10*M86 -> 963.43682
C86: % of Revenue | F86: ='Three Statement Model'!D16 -> 0.18425181 | G86: ='Three Statement Model'!E16 -> 0.34497767 | H86: ='Three Statement Model'!F16 -> 0.41773639 | I86: ='Three Statement Model'!G16 -> 0.36278915 | J86: =+OFFSET(J86,$D$4,) -> 0.28 | K86: =+OFFSET(K86,$D$4,) -> 0.2 | L86: =+OFFSET(L86,$D$4,) -> 0.15 | M86: =+OFFSET(M86,$D$4,) -> 0.0802
C87: Base | I87: 0.36 | J87: 0.25 | K87: 0.18 | L87: 0.12 | M87: 0.0802
C88: Bull | I88: 0.3 | J88: 0.2 | K88: 0.15 | L88: 0.1 | M88: 0.0802
C89: Bear | I89: 0.4 | J89: 0.28 | K89: 0.2 | L89: 0.15 | M89: 0.0802 | N89: capex = depreciation converges
C91: Tax Rate | I91: =+OFFSET(I91,$D$4,) -> 0.081 | J91: =+OFFSET(J91,$D$4,) -> 0.09 | K91: =+OFFSET(K91,$D$4,) -> 0.12 | L91: =+OFFSET(L91,$D$4,) -> 0.18 | M91: =+OFFSET(M91,$D$4,) -> 0.21
C92: Base | I92: 0.081 | J92: 0.12 | K92: 0.13 | L92: 0.15 | M92: 0.16
C93: Bull | I93: 0.081 | J93: 0.12 | K93: 0.12 | L93: 0.14 | M93: 0.15
C94: Bear | I94: 0.081 | J94: 0.09 | K94: 0.12 | L94: 0.18 | M94: 0.21
C96: Other Current Liabilities | I96: =I97*H25 -> 181.611 | J96: =J97*I25 -> 169.2333 | K96: =K97*J25 -> 295.26541 | L96: =L97*K25 -> 383.84504 | M96: =M97*L25 -> 498.99855
C97: % of COGS | F97: =F96/F25 -> 0 | G97: =G96/G25 -> 0 | H97: =H96/H25 -> 0 | I97: =+OFFSET(I97,$D$4,) -> 0.09 | J97: =+OFFSET(J97,$D$4,) -> 0.09 | K97: =+OFFSET(K97,$D$4,) -> 0.09 | L97: =+OFFSET(L97,$D$4,) -> 0.09 | M97: =+OFFSET(M97,$D$4,) -> 0.09
C98: Base | I98: 0.065 | J98: 0.065 | K98: 0.065 | L98: 0.065 | M98: 0.065
C99: Bull | I99: 0.04 | J99: 0.04 | K99: 0.04 | L99: 0.04 | M99: 0.04
C100: Bear | I100: 0.09 | J100: 0.09 | K100: 0.09 | L100: 0.09 | M100: 0.09
C102: Current Portion of Leases | I102: =I103*H25 -> 50.4475 | J102: =J103*I25 -> 47.00925 | K102: =K103*J25 -> 82.01817 | L102: =L103*K25 -> 106.62362 | M102: =M103*L25 -> 138.61071
C103: % of COGS | F103: =F102/H25 -> 0 | G103: =G102/I25 -> 0 | H103: =H102/J25 -> 0 | I103: =+OFFSET(I103,$D$4,) -> 0.025 | J103: =+OFFSET(J103,$D$4,) -> 0.025 | K103: =+OFFSET(K103,$D$4,) -> 0.025 | L103: =+OFFSET(L103,$D$4,) -> 0.025 | M103: =+OFFSET(M103,$D$4,) -> 0.025
C104: Base | I104: 0.015 | J104: 0.015 | K104: 0.015 | L104: 0.015 | M104: 0.015
C105: Bull | I105: 0.01 | J105: 0.01 | K105: 0.01 | L105: 0.01 | M105: 0.01
C106: Bear | I106: 0.025 | J106: 0.025 | K106: 0.025 | L106: 0.025 | M106: 0.025
C108: Interest Expense | I108: =I109*I10 -> 50.4756 | J108: =J109*I25 -> 22.56444 | K108: =K109*J25 -> 39.368722 | L108: =L109*K25 -> 51.179338 | M108: =M109*L25 -> 66.53314
C109: %Revenue | F109: =F108/H25 -> 0 | G109: =G108/I25 -> 0 | H109: =H108/J25 -> 0 | I109: =+OFFSET(I109,$D$4,) -> 0.012 | J109: =+OFFSET(J109,$D$4,) -> 0.012 | K109: =+OFFSET(K109,$D$4,) -> 0.012 | L109: =+OFFSET(L109,$D$4,) -> 0.012 | M109: =+OFFSET(M109,$D$4,) -> 0.012
C110: Base | I110: 0.01 | J110: 0.01 | K110: 0.01 | L110: 0.01 | M110: 0.01
C111: Bull | I111: 0.008 | J111: 0.008 | K111: 0.008 | L111: 0.008 | M111: 0.008
C112: Bear | I112: 0.012 | J112: 0.012 | K112: 0.012 | L112: 0.012 | M112: 0.012
C114: Share Repurchases | I114: =F10*I115 -> 14.662 | J114: =G10*J115 -> 13.0965 | K114: =H10*K115 -> 16.593 | L114: =I10*L115 -> 21.0315 | M114: =J10*M115 -> 27.33939
C115: % of Revenue | F115: =F114/(F19+F10) -> 0 | G115: =G114/(G19+G10) -> 0 | H115: =H114/(H19+H10) -> 0 | I115: =+OFFSET(I115,$D$4,) -> 0.005 | J115: =+OFFSET(J115,$D$4,) -> 0.005 | K115: =+OFFSET(K115,$D$4,) -> 0.005 | L115: =+OFFSET(L115,$D$4,) -> 0.005 | M115: =+OFFSET(M115,$D$4,) -> 0.005
C116: Base | I116: 0.02 | J116: 0.02 | K116: 0.02 | L116: 0.02 | M116: 0.02
C117: Bull | I117: 0.04 | J117: 0.04 | K117: 0.04 | L117: 0.04 | M117: 0.04
C118: Bear | I118: 0.005 | J118: 0.005 | K118: 0.005 | L118: 0.005 | M118: 0.005
C120: Comprehensive Income & Other | I120: =I10*I121 -> -42.063 | J120: =(G19+G25)*J121 -> -24.919878 | K120: =(H19+H25)*K121 -> -20.181743 | L120: =(I19+I25)*L121 -> -18.8064 | M120: =(J19+J25)*M121 -> -32.809968
C121: % of Revenue | F121: =-F120/(F10+F19) -> 0 | G121: =-G120/(G10+G19) -> 0 | H121: =H120/(H10+H19) -> 0 | I121: =+OFFSET(I121,$D$4,) -> -0.01 | J121: =+OFFSET(J121,$D$4,) -> -0.01 | K121: =+OFFSET(K121,$D$4,) -> -0.01 | L121: =+OFFSET(L121,$D$4,) -> -0.01 | M121: =+OFFSET(M121,$D$4,) -> -0.01
...

Sheet Metrics & Drivers
B2: Metrics & Drivers | G2: Case
B3: $ in millions, unless otherwise noted | G3: =Cover!$G$21 -> 3
B5: For Fiscal Year Ending | F5: 2021 | G5: =F5+1 -> 2022 | H5: =G5+1 -> 2023 | I5: =H5+1 -> 2024 | J5: =I5+1 -> 2025 | K5: =J5+1 -> 2026 | L5: =K5+1 -> 2027 | M5: =L5+1 -> 2028
A7: x | B7: Revenue Build
B9: Revenue
B10: % of revenue | I10: =OFFSET(I37,$G$3,0)
B11: Base
B12: Bull
B13: Bear
B15: Modules Sold per year
B16: % Growth | I16: =OFFSET(I37,$G$3,0)
B17: Base
B18: Bull
B19: Bear
A34: x | B34: Other Metrics & Drivers
B36: Cost of Goods Sold
B37: % of revenue | I37: =OFFSET(I37,$G$3,0)
B38: Base
B39: Bull
B40: Bear
B42: SG&A Expense
B43: % of revenue
B44: Base
B45: Bull
B46: Bear
B48: D&A Expense
B49: % of capex
B50: Base
B51: Bull
... B130: Bear

Sheet Additional Schedules
B2: Additional Schedules
B3: $ in millions, unless otherwise noted
B5: For Fiscal Year Ending | F5: 2021 | G5: =F5+1 -> 2022 | H5: =G5+1 -> 2023 | I5: =H5+1 -> 2024 | J5: =I5+1 -> 2025 | K5: =J5+1 -> 2026 | L5: =K5+1 -> 2027 | M5: =L5+1 -> 2028
B7: Net Working Capital
B9: Current Operating Asset 1
B10: Current Operating Asset 2
B11: Current Operating Asset 3
B12: Current Operating Asset 4
B13: Total Current Operating Assets
B15: Current Operating Liability 1
B16: Current Operating Liability 2
B17: Current Operating Liability 3
B18: Current Operating Liability 4
B19: Total Current Operating Liabilities
B21: Net Working Capital
B22: Change in Net Working Capital

Sheet Three Statement Model
B5: Assumptions & Drivers
B7: All figures in USD Millions unless stated | D7: 2021A | E7: 2022A | F7: 2023A | G7: 2024A | H7: 2025E | I7: 2026E | J7: 2027E | K7: 2028E
B9: Days in Period | D9: 365 | E9: 365 | F9: 365 | G9: =365+1 -> 366 | H9: 365 | I9: 365 | J9: 365 | K9: =365+1 -> 366
B11: Income Statement
B12: Sales Growth | E12: =E32/D32-1 -> -0.10677261 | F12: =F32/E32-1 -> 0.26697973 | G12: =G32/F32-1 -> 0.26749232 | H12: =Assumptions!J11 -> 0.29992583 | I12: =Assumptions!K11 -> 0.3 | J12: =Assumptions!L11 -> 0.3 | K12: =Assumptions!M11 -> 0.3
B13: Gross Margin | D13: =D34/D32 -> 0.38731756 | E13: =E34/E32 -> 0.23204673 | F13: =F34/F32 -> 0.4861086 | G13: =G34/G32 -> 0.55296341 | H13: =(1-Assumptions!J26) -> 0.4 | I13: =(1-Assumptions!K26) -> 0.4 | J13: =(1-Assumptions!L26) -> 0.4 | K13: =(1-Assumptions!M26) -> 0.4
B14: SG&A | D14: =D36 -> 170.3 | E14: =E36 -> 164.7 | F14: =F36 -> 197.6 | G14: =G36 -> 188.3 | H14: =G14*(1+Assumptions!J32) -> 205.247 | I14: =H14*(1+Assumptions!K32) -> 223.71923 | J14: =I14*(1+Assumptions!L32) -> 243.85396 | K14: =J14*(1+Assumptions!M32) -> 265.80082
B15: Research Expense (Percent of Sales) | D15: =D37/D32 -> 0.033794844 | E15: =E37/E32 -> 0.043064941 | F15: =F37/F32 -> 0.045892846 | G15: =G37/G32 -> 0.045503174 | H15: =Assumptions!I38 -> 0.039 | I15: =Assumptions!J38 -> 0.039 | J15: =Assumptions!K38 -> 0.039 | K15: =Assumptions!L38 -> 0.039
B16: Capital Expenditure % of Revenue | D16: =D118/D32*-1 -> 0.18425181 | E16: =E118/E32*-1 -> 0.34497767 | F16: =F118/F32*-1 -> 0.41773639 | G16: =G118/G32*-1 -> 0.36278915 | H16: =Assumptions!J86 -> 0.28 | I16: =Assumptions!K86 -> 0.2 | J16: =Assumptions!L86 -> 0.15 | K16: =Assumptions!M86 -> 0.0802 | L16: Converges to D&A
B17: Interest Expense % of Revenue | D17: =D44/D32 -> -0.0044673305 | E17: =E44/E32 -> -0.004657733 | F17: =F44/F32 -> -0.0039173145 | G17: =G44/G32 -> -0.0092480327 | H17: =Assumptions!I109*-1 -> -0.012 | I17: =Assumptions!J109*-1 -> -0.012 | J17: =Assumptions!K109*-1 -> -0.012 | K17: =Assumptions!L109*-1 -> -0.012
B18: Depreciation (Percent of Sales) | D18: =D106/D32 -> 0.083071887 | E18: =E106/E32 -> 0.096705227 | F18: =F106/F32 -> 0.087988911 | G18: =G106/G32 -> 0.09680717 | H18: =Assumptions!I44 -> 0.12 | I18: =Assumptions!J44 -> 0.12 | J18: =Assumptions!K44 -> 0.12 | K18: =Assumptions!L44 -> 0.12
B19: Tax Rate (Percent of EBT) | D19: =D50/D48*-1 -> -0.18087986 | E19: - | F19: =F50/F48*-1 -> -0.067942863 | G19: =G50/G48*-1 -> -0.081296481 | H19: =Assumptions!J91*-1 -> -0.09 | I19: =Assumptions!K91*-1 -> -0.12 | J19: =Assumptions!L91*-1 -> -0.18 | K19: =Assumptions!M91*-1 -> -0.21
B21: Balance Sheet
B22: Capital Asset Turnover Ratio | C22: (x) | D22: =D32/D71 -> 0.95381213 | E22: =E32/E71 -> 0.72155037 | F22: =F32/F71 -> 0.73766338 | G22: =G32/G71 -> 0.75690995 | H22: =AVERAGE($E22:G22) -> 0.7387079 | I22: =AVERAGE($E22:H22) -> 0.7387079 | J22: =AVERAGE($E22:I22) -> 0.7387079 | K22: =AVERAGE($E22:J22) -> 0.7387079
B23: Receivable Days (Sales Basis) | C23: (Days) | D23: =D62/D32*D9 -> 59.086584 | E23: =E62/E32*E9 -> 45.191272 | F23: =F62/F32*F9 -> 72.67884 | G23: =G62/G32*G9 -> 109.79217 | H23: =Assumptions!I62 -> 55 | I23: =Assumptions!J62 -> 55 | J23: =Assumptions!K62 -> 55 | K23: =Assumptions!L62 -> 55
B24: Inventory Days (COGS Basis) | C24: (Days) | D24: =D63/-D33*D9 -> 158.13829 | E24: =E63/-E33*E9 -> 133.51578 | F24: =F63/-F33*F9 -> 207.1986 | G24: =G63/-G33*G9 -> 252.76281 | H24: =AVERAGE($E24:G24) -> 197.82573 | I24: =AVERAGE($E24:H24) -> 197.82573 | J24: =AVERAGE($E24:I24) -> 197.82573 | K24: =AVERAGE($E24:J24) -> 197.82573
B25: Payable Days (COGS Basis) | C25: (Days) | D25: =D77/-D33*D9 -> 39.270467 | E25: =E77/-E33*E9 -> 61.949292 | F25: =F77/-F33*F9 -> 44.346194 | G25: =G77/-G33*G9 -> 93.856635 | H25: =Assumptions!I80 -> 35 | I25: =Assumptions!J80 -> 35 | J25: =Assumptions!K80 -> 35 | K25: =Assumptions!L80 -> 35
B26: Long Term Debt | D26: =D85 -> 236 | E26: =E85 -> 184.3 | F26: =F85 -> 464.1 | G26: =G85 -> 373.3 | H26: =AVERAGE($E26:G26) -> 340.56667 | I26: =AVERAGE($E26:H26) -> 340.56667 | J26: =AVERAGE($E26:I26) -> 340.56667 | K26: =AVERAGE($E26:J26) -> 340.56667
B28: Income Statement
B30: All figures in USD Millions unless stated | D30: =D$7 -> 2021A | E30: =E$7 -> 2022A | F30: =F$7 -> 2023A | G30: =G$7 -> 2024A | H30: =H$7 -> 2025E | I30: =I$7 -> 2026E | J30: =J$7 -> 2027E | K30: =K$7 -> 2028E
B32: Total Revenue | D32: 2932.4 | E32: 2619.3 | F32: 3318.6 | G32: 4206.3 | H32: =Assumptions!J10 -> 5467.878 | I32: =H32*(1+I12) -> 7108.2414 | J32: =I32*(1+J12) -> 9240.7138 | K32: =J32*(1+K12) -> 12012.928
B33: Cost Of Goods Sold | D33: =-2040.23+D38 -> -1796.63 | E33: =-2264.8+E38 -> -2011.5 | F33: =-1997.4+F38 -> -1705.4 | G33: =-2287.57+G38 -> -1880.37 | H33: =(1-H13)*H32*-1 -> -3280.7268 | I33: =(1-I13)*I32*-1 -> -4264.9448 | J33: =(1-J13)*J32*-1 -> -5544.4283 | K33: =(1-K13)*K32*-1 -> -7207.7568
B34: Gross Profit | D34: =SUM(D32,D33) -> 1135.77 | E34: =SUM(E32,E33) -> 607.8 | F34: =SUM(F32,F33) -> 1613.2 | G34: =SUM(G32,G33) -> 2325.93 | H34: =SUM(H32,H33) -> 2187.1512 | I34: =SUM(I32,I33) -> 2843.2966 | J34: =SUM(J32,J33) -> 3696.2855 | K34: =SUM(K32,K33) -> 4805.1712
B36: Selling General & Admin Exp. | D36: 170.3 | E36: 164.7 | F36: 197.6 | G36: 188.3 | H36: =H14 -> 205.247 | I36: =I14 -> 223.71923 | J36: =J14 -> 243.85396 | K36: =K14 -> 265.80082
B37: R & D Exp. | D37: 99.1 | E37: 112.8 | F37: 152.3 | G37: 191.4 | H37: =H15*H32 -> 213.24724 | I37: =I15*I32 -> 277.22141 | J37: =J15*J32 -> 360.38784 | K37: =K15*K32 -> 468.50419
B38: Depreciation & Amort. | D38: 243.6 | E38: 253.3 | F38: 292 | G38: 407.2 | H38: =-H149 -> 666.864 | I38: =-I149 -> 770.56102 | J38: =-J149 -> 848.69149 | K38: =-K149 -> 913.18136
B39: Other Operating Expenses | D39: 21.1 | E39: 73 | F39: 64.7 | G39: 84.5 | H39: =G33*Assumptions!I97*-1 -> 169.2333 | I39: =H33*Assumptions!J97*-1 -> 295.26541 | J39: =I33*Assumptions!K97*-1 -> 383.84504 | K39: =J33*Assumptions!L97*-1 -> 498.99855
B40: Total Operating Expenses | D40: =SUM(D36:D39) -> 534.1 | E40: =SUM(E36:E39) -> 603.8 | F40: =SUM(F36:F39) -> 706.6 | G40: =SUM(G36:G39) -> 871.4 | H40: =SUM(H36:H39) -> 1254.5915 | I40: =SUM(I36:I39) -> 1566.7671 | J40: =SUM(J36:J39) -> 1836.7783 | K40: =SUM(K36:K39) -> 2146.4849
B42: EBIT (Operating Income) | D42: =D34-D40 -> 601.67 | E42: =E34-E40 -> 4 | F42: =F34-F40 -> 906.6 | G42: =G34-G40 -> 1454.53 | H42: =H34-H40 -> 932.55966 | I42: =I34-I40 -> 1276.5295 | J42: =J34-J40 -> 1859.5072 | K42: =K34-K40 -> 2658.6863
B44: Interest Expense | D44: -13.1 | E44: -12.2 | F44: -13 | G44: -38.9 | H44: =H17*G85 -> -4.4796 | I44: =I17*H85 -> -3.39 | J44: =J17*I85 -> -2.3004 | K44: =K17*J85 -> -1.2108
B45: Interest and Invest. Income | D45: 0.033 | E45: 33.2 | F45: 19.09 | G45: 17.586 | H45: =G45 -> 17.586 | I45: =H45 -> 17.586 | J45: =I45 -> 17.586 | K45: =J45 -> 17.586 | L45: Flatline
B46: Foreign Currency Loss | D46: -16.4 | E46: -16.4 | F46: -21.5 | G46: =F46/F32*G32 -> -27.251085 | H46: =G46/G32*H32 -> -35.424389 | I46: =H46/H32*I32 -> -46.051706 | J46: =I46/I32*J32 -> -59.867217 | K46: =J46/J32*K32 -> -77.827382 | L46: %Revenue
B47: Net Interest Exp. | D47: =SUM(D44:D46) -> -29.467 | E47: =SUM(E44:E46) -> 4.6 | F47: =SUM(F44:F46) -> -15.41 | G47: =SUM(G44:G46) -> -48.565085 | H47: =SUM(H44:H46) -> -22.317989 | I47: =SUM(I44:I46) -> -31.855706 | J47: =SUM(J44:J46) -> -44.581617 | K47: =SUM(K44:K46) -> -61.452182
B48: Earnings Before Taxes | D48: =D42+D47 -> 572.203 | E48: =E42+E47 -> 8.6 | F48: =F42+F47 -> 891.19 | G48: =G42+G47 -> 1405.9649 | H48: =H42+H47 -> 910.24167 | I48: =I42+I47 -> 1244.6738 | J48: =J42+J47 -> 1814.9256 | K48: =K42+K47 -> 2597.2341
B50: Taxes | D50: 103.5 | E50: 52.8 | F50: 60.55 | G50: 114.3 | H50: =H32*H19*-1 -> 492.10902 | I50: =I32*I19*-1 -> 852.98897 | J50: =J32*J19*-1 -> 1663.3285 | K50: =K32*K19*-1 -> 2522.7149
B51: Net Income | D51: =D48-D50 -> 468.703 | E51: =E48-E50 -> -44.2 | F51: =F48-F50 -> 830.64 | G51: =G48-G50 -> 1291.6649 | H51: =H48-H50 -> 418.13265 | I51: =I48-I50 -> 391.68481 | J51: =J48-J50 -> 151.5971 | K51: =K48-K50 -> 74.519215
B53: Dividends | D53: 0 | E53: 0 | F53: 0 | G53: 0 | H53: =G53 -> 0 | I53: =H53 -> 0 | J53: =I53 -> 0 | K53: =J53 -> 0
B55: Balance Sheet
B57: All figures in USD Millions unless stated | D57: =D$7 -> 2021A | E57: =E$7 -> 2022A | F57: =F$7 -> 2023A | G57: =G$7 -> 2024A | H57: =H$7 -> 2025E | I57: =I$7 -> 2026E | J57: =J$7 -> 2027E | K57: =K$7 -> 2028E
B59: Assets
B60: Cash And Equivalents | D60: 1450.7 | E60: 1481.3 | F60: 1947.3 | G60: 1621.4 | H60: =H138 -> 808.10285 | I60: =I138 -> 108.45346 | J60: =J138 -> -822.44605 | K60: =K138 -> -1463.9283
B61: Short Term Investments | D61: 375.4 | E61: 1096.7 | F61: 155.5 | G61: 171.6 | H61: =G61 -> 171.6 | I61: =H61 -> 171.6 | J61: =I61 -> 171.6 | K61: =J61 -> 171.6 | L61: Flatline
B62: Trade and Other Receivables | D62: 474.7 | E62: 324.3 | F62: 660.8 | G62: 1261.8 | H62: =H23/H9*H32 -> 823.92682 | I62: =I23/I9*I32 -> 1071.1049 | J62: =J23/J9*J32 -> 1392.4363 | K62: =K23/K9*K32 -> 1805.2214
B63: Inventory | D63: 778.4 | E63: 735.8 | F63: 968.1 | G63: 1298.6 | H63: =H33*H24/H9*-1 -> 1778.1156 | I63: =I33*I24/I9*-1 -> 2311.5502 | J63: =J33*J24/J9*-1 -> 3005.0153 | K63: =K33*K24/K9*-1 -> 3895.8463
B64: Prepaid Exp. | D64: 28.2 | E64: 43.3 | F64: 62.5 | G64: 75.3 | H64: 70 | I64: 70 | J64: 70 | K64: 70 | L64: Flatline
B65: Restricted Cash | D65: - | E65: 1.032 | F65: 8.3 | G65: 1.489 | H65: 1.489 | I65: 1.489 | J65: 1.489 | K65: 1.489
B66: Other Current Assets | D66: 102.4 | E66: 101.6 | F66: 107.6 | G66: 127.1 | H66: 127.1 | I66: 127.1 | J66: 127.1 | K66: 127.1 | L66: Flatline
B67: Total Current Assets | D67: =SUM(D60:D66) -> 3209.8 | E67: =SUM(E60:E66) -> 3784.032 | F67: =SUM(F60:F66) -> 3910.1 | G67: =SUM(G60:G66) -> 4557.289 | H67: =SUM(H60:H66) -> 3780.3342 | I67: =SUM(I60:I66) -> 3861.2976 | J67: =SUM(J60:J66) -> 3945.1946 | K67: =SUM(K60:K66) -> 4607.3285
B69: Gross Property, Plant & Equipment | D69: 4370.3 | E69: 5092.9 | F69: 6192.9 | G69: 7648.4
B70: Accumulated Depreciation | D70: -1295.9 | E70: -1462.8 | F70: -1694.1 | G70: -2091.2
B71: Net Property, Plant & Equipment | D71: =D69+D70 -> 3074.4 | E71: =E69+E70 -> 3630.1 | F71: =F69+F70 -> 4498.8 | G71: =G69+G70 -> 5557.2 | H71: =H151 -> 6421.3418 | I71: =I151 -> 7072.4291 | J71: =J151 -> 7609.8447 | K71: =K151 -> 7660.1001
B73: Investments and Long-Term Assets | D73: 986.8 | E73: 705.5 | F73: 994.6 | G73: 1091.9 | H73: 1091.9 | I73: 1091.9 | J73: 1091.9 | K73: 1091.9 | L73: Flatline
B74: Total Assets | D74: =SUM(D73:D73,D67)+D71 -> 7271 | E74: =SUM(E73:E73,E67)+E71 -> 8119.632 | F74: =SUM(F73:F73,F67)+F71 -> 9403.5 | G74: =SUM(G73:G73,G67)+G71 -> 11206.389 | H74: =SUM(H73:H73,H67)+H71 -> 11293.576 | I74: =SUM(I73:I73,I67)+I71 -> 12025.627 | J74: =SUM(J73:J73,J67)+J71 -> 12646.939 | K74: =SUM(K73:K73,K67)+K71 -> 13359.329
B76: Liabilities
B77: Accounts Payable | D77: 193.3 | E77: 341.4 | F77: 207.2 | G77: 482.2 | H77: =H25*H33/365*-1 -> 314.59024 | I77: =I25*I33/365*-1 -> 408.96731 | J77: =J25*J33/365*-1 -> 531.65751 | K77: =K25*K33/365*-1 -> 691.15476
B78: Accrued Exp. | D78: 192.1 | E78: 223.3 | F78: 308.7 | G78: 310.3 | H78: =H33*Assumptions!J109*-1 -> 39.368722 | I78: =I33*Assumptions!K109*-1 -> 51.179338 | J78: =J33*Assumptions!L109*-1 -> 66.53314 | K78: =K33*Assumptions!M109*-1 -> 86.493081
B79: Curr. Port. of LT Debt | D79: 14.416 | E79: 0.159 | F79: 68.097 | G79: 90.8 | H79: 90.8 | I79: 90.8 | J79: 90.8 | K79: 90.8
B80: Def Tax Liability | D80: =188.8+44.9+23.8 -> 257.5 | E80: =27.7+95.9+221.8 -> 345.4 | F80: =413.6+248 -> 661.6 | G80: =712+145.6 -> 857.6 | H80: =712+145.6 -> 857.6 | I80: =712+145.6 -> 857.6 | J80: =712+145.6 -> 857.6 | K80: =712+145.6 -> 857.6 | L80: Flatline
B81: Unearned Revenue, Curr | D81: 201.1 | E81: 263.2 | F81: 413.6 | G81: =(F81/F32)*G32 -> 524.23482 | H81: =(G81/G32)*H32 -> 681.46638 | I81: =(H81/H32)*I32 -> 885.9063 | J81: =(I81/I32)*J32 -> 1151.6782 | K81: =(J81/J32)*K32 -> 1497.1816 | L81: % of Revenue
B82: Curr. Port. of Leases | D82: - | E82: 0.517 | F82: 0.577 | G82: 2.224 | H82: 2.224 | I82: 2.224 | J82: 2.224 | K82: 2.224
B83: Total Current Liabilities | D83: =SUM(D77:D82) -> 858.416 | E83: =SUM(E77:E82) -> 1173.976 | F83: =SUM(F77:F82) -> 1659.774 | G83: =SUM(G77:G82) -> 2267.3588 | H83: =SUM(H77:H82) -> 1986.0493 | I83: =SUM(I77:I82) -> 2296.677 | J83: =SUM(J77:J82) -> 2700.4928 | K83: =SUM(K77:K82) -> 3225.4535
B85: Long-Term Debt | D85: =236 -> 236 | E85: 184.3 | F85: 464.1 | G85: 373.3 | H85: =G85-H79 -> 282.5 | I85: =H85-I79 -> 191.7 | J85: =I85-J79 -> 100.9 | K85: =J85-K79 -> 10.1
B86: Unearned Revenue Non-Curr | D86: 426.38 | E86: 607.16 | F86: 389.92 | G86: 360.63 | H86: =(G86/G37)*H37 -> 401.7939 | I86: =(H86/H37)*I37 -> 522.33207 | J86: =(I86/I37)*J37 -> 679.03169 | K86: =(J86/J37)*K37 -> 882.7412 | L86: % of Revenue
B87: Other Non-Current Liabilities | D87: 221.8 | E87: 178.5 | F87: 219.3 | G87: 217.7 | H87: 217.7 | I87: 217.7 | J87: 217.7 | K87: 217.7
B88: Total Liabilities | D88: =D85+D83+D87+D86 -> 1742.596 | E88: =E85+E83+E87+E86 -> 2143.936 | F88: =F85+F83+F87+F86 -> 2733.094 | G88: =G85+G83+G87+G86 -> 3218.9888 | H88: =H85+H83+H87+H86 -> 2888.0432 | I88: =I85+I83+I87+I86 -> 3228.409 | J88: =J85+J83+J87+J86 -> 3698.1245 | K88: =K85+K83+K87+K86 -> 4335.9947
B90: Equity
B91: Common Stock | D91: 0.1 | E91: 0.1 | F91: 0.1 | G91: 0.1 | H91: 0.1 | I91: 0.1 | J91: 0.1 | K91: 0.1
B92: Additional Paid In Capital | D92: 2871.4 | E92: 2887.5 | F92: 2890.4 | G92: 2898.4 | H92: 2898.4 | I92: 2898.4 | J92: 2898.4 | K92: 2898.4
B93: Comprehensive and Others | D93: -61.7 | E93: -96.4 | F93: -191.8 | G93: -174.1 | H93: -174.1 | I93: -174.1 | J93: -174.1 | K93: -174.1
B94: Retained Earnings | D94: =2718.5 -> 2718.5 | E94: =3184.5 -> 3184.5 | F94: =3971.71 -> 3971.71 | G94: 5263 | H94: =G94+H51 -> 5681.1326 | I94: =H94+I51 -> 6072.8175 | J94: =I94+J51 -> 6224.4146 | K94: =J94+K51 -> 6298.9338
B95: Total Common Equity | D95: =SUM(D91:D94) -> 5528.3 | E95: =SUM(E91:E94) -> 5975.7 | F95: =SUM(F91:F94) -> 6670.41 | G95: =SUM(G91:G94) -> 7987.4 | H95: =SUM(H91:H94) -> 8405.5326 | I95: =SUM(I91:I94) -> 8797.2175 | J95: =SUM(J91:J94) -> 8948.8146 | K95: =SUM(K91:K94) -> 9023.3338
B97: Total Liabilities And Equity | D97: =D95+D88 -> 7270.896 | E97: =E95+E88 -> 8119.636 | F97: =F95+F88 -> 9403.504 | G97: =G95+G88 -> 11206.389 | H97: =H95+H88 -> 11293.576 | I97: =I95+I88 -> 12025.626 | J97: =J95+J88 -> 12646.939 | K97: =K95+K88 -> 13359.328
D98: =D97-D74 -> -0.104 | E98: =E97-E74 -> 0.004 | F98: =F97-F74 -> 0.004 | G98: =G97-G74 -> -0.00017808714 | H98: =H97-H74 -> -0.00017808714 | I98: =I97-I74 -> -0.00017808715 | J98: =J97-J74 -> -0.00017808715 | K98: =K97-K74 -> -0.00017808715
B100: Cash Flow
B102: All figures in USD Millions unless stated | D102: =D$7 -> 2021A | E102: =E$7 -> 2022A | F102: =F$7 -> 2023A | G102: =G$7 -> 2024A | H102: =H$7 -> 2025E | I102: =I$7 -> 2026E | J102: =J$7 -> 2027E | K102: =K$7 -> 2028E
B104: Cash Flows from Operating Activities
B105: Net Income | D105: =D51 -> 468.703 | E105: =E51 -> -44.2 | F105: =F51 -> 830.64 | G105: =G51 -> 1291.6649 | H105: =H51 -> 418.13265 | I105: =I51 -> 391.68481 | J105: =J51 -> 151.5971 | K105: =K51 -> 74.519215
B106: Depreciation & Amort., Total | D106: =D38 -> 243.6 | E106: =E38 -> 253.3 | F106: =F38 -> 292 | G106: =G38 -> 407.2 | H106: =H38 -> 666.864 | I106: =I38 -> 770.56102 | J106: =J38 -> 848.69149 | K106: =K38 -> 913.18136
B108: Change in Acc. Receivable | D108: 118.724 | E108: 118.7 | F108: -304.2 | G108: =G62-F62 -> 601 | H108: =-H62+G62 -> 437.87318 | I108: =-I62+H62 -> -247.17805 | J108: =-J62+I62 -> -321.33146 | K108: =-K62+J62 -> -412.78509
B109: Change in Inventory | D109: 16.69 | E109: 16.7 | F109: -205.1 | G109: -276.8 | H109: =-H63+G63 -> -479.51556 | I109: =-I63+H63 -> -533.43467 | J109: =-J63+I63 -> -693.46507 | K109: =-K63+J63 -> -890.83104
B110: Government Grants Receivable | D110: - | E110: - | F110: -659.75 | G110: 270.3 | H110: =-H64+G64 -> 5.3 | I110: =-I64+H64 -> 0 | J110: =-J64+I64 -> 0 | K110: =-K64+J64 -> 0
B111: Change in Acc. Payable | D111: 49 | E111: 5.6 | F111: 79.3 | G111: 268.7 | H111: =H77-G77 -> -167.60976 | I111: =I77-H77 -> 94.377072 | J111: =J77-I77 -> 122.69019 | K111: =K77-J77 -> 159.49725
B112: Deferred Revenue Total | D112: 912.9 | E112: 783.2 | F112: 912.9 | G112: 0.7 | H112: =H86-G86+H81-G81 -> 198.39546 | I112: =I86-H86+I81-H81 -> 324.97809 | J112: =J86-I86+J81-I81 -> 422.47151 | K112: =K86-J86+K81-J81 -> 549.21296
B113: Change in Accrued Expenses | D113: -86.6 | E113: 165 | F113: 223 | G113: 371.9 | H113: =H78-G78 -> -270.93128 | I113: =I78-H78 -> 11.810616 | J113: =J78-I78 -> 15.353801 | K113: =K78-J78 -> 19.959942
B114: Change in Other Net Operating Assets | D114: =-186.4-253.511-145.281-188 -> -773.192 | E114: -215.7 | F114: 556.6 | G114: -17.8 | H114: =-H66+G66 -> 0 | I114: =-I66+H66 -> 0 | J114: =-J66+I66 -> 0 | K114: =-K66+J66 -> 0 | L114: Incl Sales of Buisness, Sale of systems
B115: Cash flow from Operating Activities | D115: =SUM(D108:D114) -> 237.522 | E115: =SUM(E108:E114) -> 873.5 | F115: =SUM(F108:F114) -> 602.75 | G115: =SUM(G108:G114) -> 1218 | H115: =SUM(H105:H114) -> 808.50869 | I115: =SUM(I105:I114) -> 812.79889 | J115: =SUM(J105:J114) -> 546.00756 | K115: =SUM(K105:K114) -> 412.75461
B117: Investing Activities
B118: Capital Expenditure (Including PPE Acquisition) | D118: -540.3 | E118: -903.6 | F118: -1386.3 | G118: =-1526 -> -1526 | H118: =-H146 -> -1531.0058 | I118: =-I146 -> -1421.6483 | J118: =-J146 -> -1386.1071 | K118: =-K146 -> -963.43682 | L118: converge terminal year to depreciation
B119: Divestitures & Equity Security | D119: =300.5+147.5 -> 448 | E119: =442.3-728.3 -> -286 | F119: =7.7+9515.1 -> 9522.8 | G119: =-24.2 -> -24.2 | H119: 0 | I119: 0 | J119: 0 | K119: 0
B120: Cash flows from Investing Activities | D120: -7.457 | E120: 85.092 | F120: 114.129 | G120: -30.235 | H120: =SUM(H118:H119) -> -1531.0058 | I120: =SUM(I118:I119) -> -1421.6483 | J120: =SUM(J118:J119) -> -1386.1071 | K120: =SUM(K118:K119) -> -963.43682
B122: Financing Activities
B123: Total Debt Issued | D123: 129.2 | E123: 397.4 | F123: 368 | G123: 258.5
B124: Total Debt Repaid | D124: -72.7 | E124: -75.9 | F124: - | G124: -205.8
B125: Net Increase/(Decrease) in Debt | D125: =SUM(D123:D124) -> 56.5 | E125: =SUM(E123:E124) -> 321.5 | F125: =SUM(F123:F124) -> 368 | G125: =SUM(G123:G124) -> 52.7 | H125: =-G79 -> -90.8 | I125: =-H79 -> -90.8 | J125: =-I79 -> -90.8 | K125: =-J79 -> -90.8 | L125: I'M JUST ASSUMING THE LONG-TERM DEBT DOESN’T INCREASE EVER AND THEY ARE JUST STEADILY REPAYING THEIR DEBT
B127: Issuance of Common Stock | D127: - | E127: - | F127: - | G127: - | H127: - | I127: - | J127: - | K127: -
B128: Repurchase of Common Stock | D128: -16 | E128: -12.1 | F128: -31.1 | G128: -20.2 | H128: =H91-G91 -> 0 | I128: =I91-H91 -> 0 | J128: =J91-I91 -> 0 | K128: =K91-J91 -> 0
B129: Net Increase/(Decrease) in Common Stock | D129: =SUM(D127:D128) -> -16 | E129: =SUM(E127:E128) -> -12.1 | F129: =SUM(F127:F128) -> -31.1 | G129: =SUM(G127:G128) -> -20.2 | H129: =H91-G91 -> 0 | I129: =I91-H91 -> 0 | J129: =J91-I91 -> 0 | K129: =K91-J91 -> 0
B131: Total Dividends Paid | D131: - | E131: - | F131: - | G131: - | H131: - | I131: - | J131: - | K131: -
B132: Other Financing Activities | F132: -7.6 | G132: -0.6 | H132: 0 | I132: 0 | J132: 0 | K132: 0
B133: Cash from Financing | D133: =D129+D125 -> 40.5 | E133: =E129+E125 -> 309.4 | F133: =F129+F125 -> 336.9 | G133: =G129+G125 -> 32.5 | H133: =H129+H125 -> -90.8 | I133: =I129+I125 -> -90.8 | J133: =J129+J125 -> -90.8 | K133: =K129+K125 -> -90.8
...

Sheet DCF
B2: Discounted Cash Flow Analysis
B3: $ in millions, unless otherwise noted | F3: =TODAY() -> 45982
B5: For Fiscal Year Ending | G5: 2025 | H5: =G5+1 -> 2026 | I5: =H5+1 -> 2027 | J5: =I5+1 -> 2028 | N5: Exit Multiple Method | S5: Perpetuity Growth Method
B7: Total Revenues | G7: ='Three Statement Model'!H32 -> 5467.878 | H7: ='Three Statement Model'!I32 -> 7108.2414 | I7: ='Three Statement Model'!J32 -> 9240.7138 | J7: ='Three Statement Model'!K32 -> 12012.928 | N7: =$J$5&"E Adjusted EBITDA" -> 2028E Adjusted EBITDA | Q7: =J18+J16 -> 3571.8676 | S7: =$J$5&"E Unlevered Free Cash Flow" -> 2028E Unlevered Free Cash Flow | V7: =J30 -> 660.6619 | X7: change (after you adjust your new schedule to include more years)
B8: % growth | H8: =(H7-G7)/G7 -> 0.3 | I8: =(I7-H7)/H7 -> 0.3 | J8: =(J7-I7)/I7 -> 0.3 | N8: Terminal Multiple | Q8: 9 | S8: Perpetuity Growth Rate | V8: 0.025
N9: Terminal Value | Q9: =Q8*Q7 -> 32146.809 | S9: Terminal Value | V9: =(V7*(1+V8))/(D33-V8) -> 7213.359 | Y9: Terminal Value = (2028 Cash Flow *(1 + PGR))/(WACC - PGR)
B10: Cost of Goods Sold | G10: ='Three Statement Model'!H33*-1 -> 3280.7268 | H10: ='Three Statement Model'!I33*-1 -> 4264.9448 | I10: ='Three Statement Model'!J33*-1 -> 5544.4283 | J10: ='Three Statement Model'!K33*-1 -> 7207.7568 | N10: Discount Factor | Q10: =J35 -> 0.63807022 | S10: Discount Factor | V10: =J35 -> 0.63807022 | Y10: Note that you can use this formula to solve for the "implied multiple"
B11: Gross Profit | G11: =G7-G10 -> 2187.1512 | H11: =H7-H10 -> 2843.2966 | I11: =I7-I10 -> 3696.2855 | J11: =J7-J10 -> 4805.1712 | N11: Present Value of Terminal Value | Q11: =Q10*Q9 -> 20511.921 | S11: Present Value of Terminal Value | V11: =V10*V9 -> 4602.6296 | Y11: Because Terminal Value is also Exit Multiple * Adj. EBITDA
B12: % margin | G12: =G11/G7 -> 0.4 | H12: =H11/H7 -> 0.4 | I12: =I11/I7 -> 0.4 | J12: =J11/J7 -> 0.4 | N12: Present Value of Cash Flow | Q12: =J38 -> 468.0633 | S12: Present Value of Cash Flow | V12: =J38 -> 468.0633 | Y12: So Implied Multiple = Terminal Value / Adj. EBITDA
N13: Total Enterprise Value | Q13: =SUM(Q11:Q12) -> 20979.984 | S13: Total Enterprise Value | V13: =V12+V11 -> 5070.6929 | Y13: Implied PGR is a bit more complicated, have to algebraically solve for PGR, kind of a pain
B14: SG&A Expense | G14: ='Three Statement Model'!H36 -> 205.247 | H14: ='Three Statement Model'!I36 -> 223.71923 | I14: ='Three Statement Model'!J36 -> 243.85396 | J14: ='Three Statement Model'!K36 -> 265.80082 | N14: Implied PGR | Q14: =((Q9*D33)-(V7))/(Q9+V7) -> 0.096346915 | S14: Implied Terminal Multiple | V14: =V9/Q7 -> 2.0194923
B15: R&D Expense | G15: ='Three Statement Model'!H37 -> 213.24724 | H15: ='Three Statement Model'!I37 -> 277.22141 | I15: ='Three Statement Model'!J37 -> 360.38784 | J15: ='Three Statement Model'!K37 -> 468.50419 | N15: Less: Debt | Q15: 891.9 | S15: Less: Debt | V15: 891.9 | Y15: Implied PGR = ((Terminal Value * WACC) - (2028 Cash Flow))/(Terminal Value + 2028 Cash Flow)
B16: D&A Expense | G16: ='Three Statement Model'!H38 -> 666.864 | H16: ='Three Statement Model'!I38 -> 770.56102 | I16: ='Three Statement Model'!J38 -> 848.69149 | J16: ='Three Statement Model'!K38 -> 913.18136 | N16: Plus: Cash | Q16: 2039.9 | S16: Plus: Cash | V16: 2039.9 | Y16: Note: Delete this text above when done
B17: Other Operating Expense | G17: ='Three Statement Model'!H39 -> 169.2333 | H17: ='Three Statement Model'!I39 -> 295.26541 | I17: ='Three Statement Model'!J39 -> 383.84504 | J17: ='Three Statement Model'!K39 -> 498.99855 | N17: Total Equity Value | Q17: =Q16+Q15+Q13 -> 23911.784 | S17: Total Equity Value | V17: =V16+V15+V13 -> 8002.4929
B18: EBIT | G18: =G11-SUM(G14:G17) -> 932.55966 | H18: =H11-SUM(H14:H17) -> 1276.5295 | I18: =I11-SUM(I14:I17) -> 1859.5072 | J18: =J11-SUM(J14:J17) -> 2658.6863 | N18: Diluted Shares Outstanding (2025) | Q18: 107.5 | S18: Diluted Shares Outstanding | V18: 107.5 | Y18: PGR actual is 3.5% given GDP is 3.8%
B19: % margin | G19: =G18/G7 -> 0.17055239 | H19: =H18/H7 -> 0.17958443 | I19: =I18/I7 -> 0.20122982 | J19: =J18/J7 -> 0.22131876 | N19: Implied Share Price | Q19: =Q17/Q18 -> 222.4352 | S19: Implied Share Price | V19: =V17/V18 -> 74.441794
N20: Upside / (Downside) | Q20: =(Q19-CurrentPrice)/CurrentPrice -> -0.095203366 | S20: Upside / (Downside) | V20: =(V19-CurrentPrice)/CurrentPrice -> -0.69719413
B21: Taxes | G21: ='Three Statement Model'!H50 -> 492.10902 | H21: ='Three Statement Model'!I50 -> 852.98897 | I21: ='Three Statement Model'!J50 -> 1663.3285 | J21: ='Three Statement Model'!K50 -> 2522.7149
B22: % effective tax rate | G22: =G21/G7 -> 0.09 | H22: =H21/H7 -> 0.12 | I22: =I21/I7 -> 0.18 | J22: =J21/J7 -> 0.21 | N22: Blended Implied Share Price
B23: Net Operating Profit After Tax | G23: =G18-G21 -> 440.45064 | H23: =H18-H21 -> 423.54051 | I23: =I18-I21 -> 196.17871 | J23: =J18-J21 -> 135.9714 | N23: Exit Multiple Method | V23: 0.5
B24: % margin | G24: =G23/G7 -> 0.080552389 | H24: =H23/H7 -> 0.05958443 | I24: =I23/I7 -> 0.021229822 | J24: =J23/J7 -> 0.011318756 | N24: Perpetuity Growth Method | V24: 0.5
N25: Blended Implied Share Price | V25: =Q19*V23+V19*V24 -> 148.4385
B26: Plus: D&A Expense | G26: =G16 -> 666.864 | H26: =H16 -> 770.56102 | I26: =I16 -> 848.69149 | J26: =J16 -> 913.18136
B27: Less: Capital Expenditures | G27: ='Three Statement Model'!H118*-1 -> 1531.0058 | H27: ='Three Statement Model'!I118*-1 -> 1421.6483 | I27: ='Three Statement Model'!J118*-1 -> 1386.1071 | J27: ='Three Statement Model'!K118*-1 -> 963.43682
B28: Less: Change in Net Working Capital | G28: =SUM('Three Statement Model'!H108:H113)*-1 -> 276.48796 | H28: =SUM('Three Statement Model'!I108:I113)*-1 -> 349.44694 | I28: =SUM('Three Statement Model'!J108:J113)*-1 -> 454.28102 | J28: =SUM('Three Statement Model'!K108:K113)*-1 -> 574.94597
B29: Less: Stub Period
B30: Unlevered Free Cash Flow | G30: =G23+G26-G27+G28 -> -147.20324 | H30: =H23+H26-H27+H28 -> 121.9002 | I30: =I23+I26-I27+I28 -> 113.04416 | J30: =J23+J26-J27+J28 -> 660.6619
B31: % margin | G31: =G30/G7 -> -0.026921457 | H31: =H30/H7 -> 0.017149136 | I31: =I30/I7 -> 0.012233271 | J31: =J30/J7 -> 0.05499591
B33: WACC | D33: =WACC!$J$23 -> 0.11887838 | G33: =$D$33 -> 0.11887838 | H33: =$D$33 -> 0.11887838 | I33: =$D$33 -> 0.11887838 | J33: =$D$33 -> 0.11887838
B34: Discount Period | G34: =F34+1 -> 1 | H34: =G34+1 -> 2 | I34: =H34+1 -> 3 | J34: =I34+1 -> 4
B35: Discount Factor | G35: =1/(1+G33)^G34 -> 0.89375219 | H35: =1/(1+H33)^H34 -> 0.79879297 | I35: =1/(1+I33)^I34 -> 0.71392297 | J35: =1/(1+J33)^J34 -> 0.63807022
B36: Present Value of Unlevered Free Cash Flow | G36: =G30*G35 -> -131.56322 | H36: =H30*H35 -> 97.373021 | I36: =I30*I35 -> 80.704819 | J36: =J30*J35 -> 421.54868
B38: Sum of Present Value Cash Flows | J38: =SUM(G36:J36) -> 468.0633
B41: DCF Sensitivity Analysis: Upside / (Downside) - Exit Multiple Method
D42: Exit Multiple
C43: =Q17/Q18 -> 222.4352 | D43: 8.2 | E43: 8.7 | F43: 9.2 | G43: 9.7 | H43: 10.2 | I43: 10.7 | J43: 11.2
B44: WACC | C44: 0.077 | D44: 234.89433 | E44: 247.24226 | F44: 259.59018 | G44: 271.93811 | H44: 284.28604 | I44: 296.63397 | J44: 308.9819
C45: 0.082 | D45: 231.07841 | E45: 243.19967 | F45: 255.32094 | G45: 267.4422 | H45: 279.56346 | I45: 291.68472 | J45: 303.80599
C46: 0.087 | D46: 227.3496 | E46: 239.24937 | F46: 251.14915 | G46: 263.04892 | H46: 274.94869 | I46: 286.84847 | J46: 298.74824
C47: =WACC!$J$23 -> 0.11887838 | D47: 205.47444 | E47: 216.07492 | F47: 226.6754 | G47: 237.27587 | H47: 247.87635 | I47: 258.47682 | J47: 269.0773
C48: 0.097 | D48: 220.14386 | E48: 231.61563 | F48: 243.0874 | G48: 254.55917 | H48: 266.03093 | I48: 277.5027 | J48: 288.97447
C49: 0.102 | D49: 216.66241 | E49: 227.92739 | F49: 239.19237 | G49: 250.45735 | H49: 261.72234 | I49: 272.98732 | J49: 284.2523
C50: 0.107 | D50: 213.259 | E50: 224.32183 | F50: 235.38467 | G50: 246.4475 | H50: 257.51033 | I50: 268.57317 | J50: 279.636
B52: DCF Sensitivity Analysis: Upside / (Downside) - Perpetuity Growth Method
D53: Perpetuity Growth
C54: =V17/V18 -> 74.441794 | D54: 0.0175 | E54: 0.02 | F54: 0.0225 | G54: 0.025 | H54: 0.0275 | I54: 0.03 | J54: 0.0325
B55: WACC | C55: 0.077 | D55: 110.50169 | E55: 114.12806 | F55: 118.08712 | G55: 122.42686 | H55: 127.20496 | I55: 132.49137 | J55: 138.37176
C56: 0.082 | D56: 103.02505 | E56: 106.05809 | F56: 109.346 | G56: 112.92233 | H56: 116.82676 | I56: 121.10661 | J56: 125.81878
C57: 0.087 | D57: 96.640232 | E57: 99.209223 | F57: 101.97736 | G57: 104.96873 | H57: 108.21148 | I57: 111.73869 | J57: 115.58949
C58: =WACC!$J$23 -> 0.11887838 | D58: 70.984212 | E58: 72.078459 | F58: 73.229475 | G58: 74.441794 | H58: 75.720448 | I58: 77.071035 | J58: 78.499801
C59: 0.097 | D59: 86.320824 | E59: 88.222047 | F59: 90.250869 | G59: 92.420582 | H59: 94.746388 | I59: 97.245763 | J59: 99.938887
C60: 0.102 | D60: 82.095709 | E60: 83.752606 | F60: 85.51371 | G60: 87.389171 | H60: 89.390503 | I60: 91.530816 | J60: 93.825108
C61: 0.107 | D61: 78.354081 | E61: 79.808621 | F61: 81.349229 | G61: 82.983775 | H61: 84.721124 | I61: 86.571287 | J61: 88.545623
C63: Bear | D63: ASP Sensitivity Analysis: 2028E Exit (EBITDA) Multiple Method
C64: =Cover!G21 -> 3 | D64: 0.22 | E64: =D64+0.02 -> 0.24 | F64: =E64+0.02 -> 0.26 | G64: =F64+0.02 -> 0.28 | H64: =G64+0.02 -> 0.3 | I64: =H64+0.02 -> 0.32 | J64: =I64+0.02 -> 0.34
B65: CASE # (2028) | C65: REVENUE | D65: =Assumptions!$M$13*D64 -> 9788.3117 | E65: =Assumptions!$M$13*E64 -> 10678.158 | F65: =Assumptions!$M$13*F64 -> 11568.005 | G65: =Assumptions!$M$13*G64 -> 12457.851 | H65: =Assumptions!$M$13*H64 -> 13347.698 | I65: =Assumptions!$M$13*I64 -> 14237.544 | J65: =Assumptions!$M$13*J64 -> 15127.391
C66: EBIT | D66: =D65*$J$12-SUM($J$14:$J$17) -> 1768.8398 | E66: =E65*$J$12-SUM($J$14:$J$17) -> 2124.7784 | F66: =F65*$J$12-SUM($J$14:$J$17) -> 2480.717 | G66: =G65*$J$12-SUM($J$14:$J$17) -> 2836.6556 | H66: =H65*$J$12-SUM($J$14:$J$17) -> 3192.5942 | I66: =I65*$J$12-SUM($J$14:$J$17) -> 3548.5328 | J66: =J65*$J$12-SUM($J$14:$J$17) -> 3904.4714
C67: UFCF | D67: =D66*(1-$J$22)+$J$26-SUM($J$27:$J$28) -> 772.18198 | E67: =E66*(1-$J$22)+$J$26-SUM($J$27:$J$28) -> 1053.3735 | F67: =F66*(1-$J$22)+$J$26-SUM($J$27:$J$28) -> 1334.565 | G67: =G66*(1-$J$22)+$J$26-SUM($J$27:$J$28) -> 1615.7565 | H67: =H66*(1-$J$22)+$J$26-SUM($J$27:$J$28) -> 1896.948 | I67: =I66*(1-$J$22)+$J$26-SUM($J$27:$J$28) -> 2178.1395 | J67: =J66*(1-$J$22)+$J$26-SUM($J$27:$J$28) -> 2459.331
D68: =$J$35*D67 -> 492.70632 | E68: =$J$35*E67 -> 672.12624 | F68: =$J$35*F67 -> 851.54616 | G68: =$J$35*G67 -> 1030.9661 | H68: =$J$35*H67 -> 1210.386 | I68: =$J$35*I67 -> 1389.8059 | J68: =$J$35*J67 -> 1569.2258
C69: EBITDA | D69: =D66+$J$16 -> 2682.0211 | E69: =E66+$J$16 -> 3037.9597 | F69: =F66+$J$16 -> 3393.8983 | G69: =G66+$J$16 -> 3749.8369 | H69: =H66+$J$16 -> 4105.7755 | I69: =I66+$J$16 -> 4461.7141 | J69: =J66+$J$16 -> 4817.6528
C70: SHARE PRICE | D70: =(D69*$Q$8*$Q$10+$Q$12-$Q$15+$Q$16)/$Q$18 -> 158.30626 | E70: =(E69*$Q$8*$Q$10+$Q$12-$Q$15+$Q$16)/$Q$18 -> 177.32045 | F70: =(F69*$Q$8*$Q$10+$Q$12-$Q$15+$Q$16)/$Q$18 -> 196.33463 | G70: =(G69*$Q$8*$Q$10+$Q$12-$Q$15+$Q$16)/$Q$18 -> 215.34881 | H70: =(H69*$Q$8*$Q$10+$Q$12-$Q$15+$Q$16)/$Q$18 -> 234.36299 | I70: =(I69*$Q$8*$Q$10+$Q$12-$Q$15+$Q$16)/$Q$18 -> 253.37717 | J70: =(J69*$Q$8*$Q$10+$Q$12-$Q$15+$Q$16)/$Q$18 -> 272.39135

Sheet WACC
B2: Weighted Average Cost of Capital
B3: $ in millions, unless otherwise noted
B5: Inputs | G5: Cost of Debt Calculation
B6: Risk-Free Rate | E6: 0.0415
B7: Equity Risk Premium | E7: 0.05 | G7: Risk-Free Rate | J7: 0.0415
B8: Beta | E8: =J17 -> 1.59 | G8: Credit Spread on [XXX] Rating
B9: Effective Tax Rate | E9: =J10 -> 0.2557 | G9: Pre-Tax Cost of Debt | J9: 4.47
B10: Current Share Price | E10: =CurrentPrice -> 245.84 | G10: Effective Tax Rate (US Corp Tax 2025) | J10: 0.2557
B11: Diluted Shares Outstanding | E11: 107300000 | G11: After-Tax Cost of Debt | J11: =J9*(1+J10)/100 -> 0.05612979
B12: Market Value of Debt | E12: 891900000
G13: Cost of Equity Calculation
G15: Risk-Free Rate | J15: =J7 -> 0.0415
G16: Equity Risk Premium | J16: 0.05
E17: 16/11/2025 | G17: Beta | J17: 1.59
G18: Cost of Equity | J18: =J15+J16*J17 -> 0.121
B20: Weighted Average Cost of Capital Calculation | G20: Total Value | I20: % | J20: Cost
B21: Market Value of Debt | G21: =E12 -> 891900000 | I21: =G21/G23 -> 0.032705633 | J21: =J11 -> 0.05612979
B22: Market Value of Equity | G22: =E10*E11 -> 26378632000 | I22: =G22/G23 -> 0.96729437 | J22: =J18 -> 0.121
B23: Total | G23: =SUM(G21:G22) -> 27270532000 | I23: =SUM(I21:I22) -> 1 | J23: =I21*J21+I22*J22 -> 0.11887838

Sheet Comps
B2: Comparable Companies Analysis | F2: Date
B3: $ in millions, unless otherwise noted | F3: =TODAY() -> 45982
B5: Valuation Metrics
B6: Company Name | C6: Day Close Price Latest | D6: Shares Outstanding Latest | E6: Market Capitalization Latest | F6: LTM Net Debt | G6: Total Enterprise Value Latest | H6: LTM Total Revenue | I6: LTM EBITDA | J6: LTM EBIT | K6: EV / Revenue | L6: EV / EBIT | M6: NTM Forward PE (CapIQ)
B7: Canadian Solar Inc. (NasdaqGS:CSIQ) | C7: 28.47 | D7: 67 | E7: 1906.1 | F7: 4889.9 | G7: 8286.8 | H7: 5899.1 | I7: 656.7 | J7: 99 | K7: =G7/H7 -> 1.4047567 | L7: =G7/J7 -> 83.705051 | M7: NM
B8: Sunrun Inc. (NasdaqGS:RUN) | C8: 18.57 | D8: 232 | E8: 4309 | F8: 14021.7 | G8: 19991.4 | H8: 2316.7 | I8: 345.9 | J8: -357.6 | K8: =G8/H8 -> 8.6292571 | L8: =G8/J8 -> -55.904362 | M8: 30.47
B9: JinkoSolar Holding Co., Ltd. (NYSE:JKS) | C9: 30.58 | D9: 51.7 | E9: 1579.5 | F9: 2561.4 | G9: 5965.7 | H9: 9657.6 | I9: 106.9 | J9: -936.1 | K9: =G9/H9 -> 0.61772076 | L9: =G9/J9 -> -6.3729302 | M9: 22.02x
B10: JA Solar Technology Co., Ltd. (SZSE:002459) | C10: 1.95 | D10: 3267.3 | E10: 6376.1 | F10: 3138 | G10: 9529.8 | H10: 7398.1 | I10: 422 | J10: -644.5 | K10: =G10/H10 -> 1.2881415 | L10: =G10/J10 -> -14.786346 | M10: 86.36x
B11: LONGi Green Energy Technology Co., Ltd. (SHSE:601012) | C11: 2.98 | D11: 7557.9 | E11: 22490.2 | F11: -2707.8 | G11: 19847.7 | H11: 10538.7 | I11: -366.9 | J11: -1409.7 | K11: =G11/H11 -> 1.8833158 | L11: =G11/J11 -> -14.079379 | M11: NM
B12: Trina Solar Co., Ltd. (SHSE:688599) | C12: 2.92 | D12: 2160.7 | E12: 6301.9 | F12: 3919.3 | G12: 10970.4 | H12: 9441.4 | I12: 24.8 | J12: -993.7 | K12: =G12/H12 -> 1.1619463 | L12: =G12/J12 -> -11.039952 | M12: NM
B13: Enphase Energy, Inc. (NasdaqGM:ENPH) | C13: 27.53 | D13: 130.9 | E13: 3602.6 | F13: -244.3 | G13: 3358.3 | H13: 1512.4 | I13: 281.4 | J13: 207.1 | K13: =G13/H13 -> 2.2205104 | L13: =G13/J13 -> 16.215838 | M13: 13.40x
B14: Skyworks Solutions, Inc. (NasdaqGS:SWKS) | C14: 63.16 | D14: 148.7 | E14: 9390.6 | F14: -185.3 | G14: 9205.3 | H14: 4086.9 | I14: 974.7 | J14: 511.7 | K14: =G14/H14 -> 2.2523918 | L14: =G14/J14 -> 17.989642 | M14: 14.35x
B15: Sanan Optoelectronics Co.,Ltd (SHSE:600703) | C15: 1.89 | D15: 4867.6 | E15: 9197.6 | F15: 603.9 | G15: 9811.9 | H15: 2542.1 | I15: 538.1 | J15: -0.3 | K15: =G15/H15 -> 3.8597616 | L15: - | M15: 136.21x
B16: ON Semiconductor Corporation (NasdaqGS:ON) | C16: 46.02 | D16: 402.4 | E16: 18517.5 | F16: 760.3 | G16: 19298.5 | H16: 6187.8 | I16: 1859 | J16: 1221.3 | K16: =G16/H16 -> 3.1187983 | L16: =G16/J16 -> 15.801605 | M16: 17.02x | O16: ASP advanced solar power
B18: First Solar, Inc. | C18: 253.54 | D18: 107.3 | E18: 27206.9 | F18: -1148 | G18: 26058.9 | H18: 5050.6 | I18: 2018.7 | J18: 1505.7 | K18: =G18/H18 -> 5.1595652 | L18: =G18/J18 -> 17.306834 | M18: 11.56
B20: Minimum | C20: =MIN(C7:C18) -> 1.89 | D20: =MIN(D7:D18) -> 51.7 | E20: =MIN(E7:E18) -> 1579.5 | F20: =MIN(F7:F18) -> -2707.8 | G20: =MIN(G7:G18) -> 3358.3 | H20: =MIN(H7:H18) -> 1512.4 | I20: =MIN(I7:I18) -> -366.9 | J20: =MIN(J7:J18) -> -1409.7 | ... M20: =MIN(M7:M18) -> 11.56
B21: 25th Percentile | C21: =_xlfn.PERCENTILE.INC(C7:C18,0.25) -> 2.95 | D21: =_xlfn.PERCENTILE.INC(D7:D18,0.25) -> 119.1 | E21: =_xlfn.PERCENTILE.INC(E7:E18,0.25) -> 3955.8 | F21: =_xlfn.PERCENTILE.INC(F7:F18,0.25) -> -214.8 | G21: =_xlfn.PERCENTILE.INC(G7:G18,0.25) -> 8746.05 | H21: =_xlfn.PERCENTILE.INC(H7:H18,0.25) -> 3314.5 | I21: =_xlfn.PERCENTILE.INC(I7:I18,0.25) -> 194.15 | J21: =_xlfn.PERCENTILE.INC(J7:J18,0.25) -> -790.3 | ... M21: =_xlfn.PERCENTILE.INC(M7:M18,0.25) -> 16.2875
B22: Mean | C22: =AVERAGE(C7:C18) -> 43.419091 | D22: =AVERAGE(D7:D18) -> 1726.6818 | E22: =AVERAGE(E7:E18) -> 10079.818 | F22: =AVERAGE(F7:F18) -> 2328.1 | G22: =AVERAGE(G7:G18) -> 12938.609 | H22: =AVERAGE(H7:H18) -> 5875.5818 | I22: =AVERAGE(I7:I18) -> 623.75455 | J22: =AVERAGE(J7:J18) -> -72.463636 | ... M22: =AVERAGE(M7:M18) -> 21.015
B23: Median | C23: =MEDIAN(C7:C18) -> 27.53 | D23: =MEDIAN(D7:D18) -> 232 | E23: =MEDIAN(E7:E18) -> 6376.1 | F23: =MEDIAN(F7:F18) -> 760.3 | G23: =MEDIAN(G7:G18) -> 9811.9 | H23: =MEDIAN(H7:H18) -> 5899.1 | I23: =MEDIAN(I7:I18) -> 422 | J23: =MEDIAN(J7:J18) -> -0.3 | ... M23: =MEDIAN(M7:M18) -> 21.015
B24: 75th Percentile | C24: =_xlfn.PERCENTILE.INC(C7:C18,0.75) -> 38.3 | D24: =_xlfn.PERCENTILE.INC(D7:D18,0.75) -> 2714 | E24: =_xlfn.PERCENTILE.INC(E7:E18,0.75) -> 13954.05 | F24: =_xlfn.PERCENTILE.INC(F7:F18,0.75) -> 3528.65 | G24: =_xlfn.PERCENTILE.INC(G7:G18,0.75) -> 19573.1 | H24: =_xlfn.PERCENTILE.INC(H7:H18,0.75) -> 8419.75 | I24: =_xlfn.PERCENTILE.INC(I7:I18,0.75) -> 815.7 | J24: =_xlfn.PERCENTILE.INC(J7:J18,0.75) -> 359.4 | ... M24: =_xlfn.PERCENTILE.INC(M7:M18,0.75) -> 25.7425
B25: Maximum | C25: =MAX(C7:C18) -> 253.54 | D25: =MAX(D7:D18) -> 7557.9 | E25: =MAX(E7:E18) -> 27206.9 | F25: =MAX(F7:F18) -> 14021.7 | G25: =MAX(G7:G18) -> 26058.9 | H25: =MAX(H7:H18) -> 10538.7 | I25: =MAX(I7:I18) -> 2018.7 | J25: =MAX(J7:J18) -> 1505.7 | ... M25: =MAX(M7:M18) -> 30.47 | O25: =13.03*M25 -> 397.0241

Sheet FIELD
C3: Open | D3: Low | E3: High | F3: Close
B4: 52 wk avg (2025) | C4: 116.56 | D4: 116.56 | E4: 281.55 | F4: 281.55 | G4: =AVERAGE(F4,D4) -> 199.055
B5: Blended share price | C5: 134.72 | D5: 134.72 | E5: 457.79 | F5: 457.79 | G5: =AVERAGE(F5,D5) -> 296.255
B6: Perpetuity growth DCF | C6: 83 | D6: 83 | E6: 385.22 | F6: 385.22 | G6: =AVERAGE(F6,D6) -> 234.11
B7: Exit multiple DCF | C7: 208.72 | D7: 208.72 | E7: 530.36 | F7: 530.36 | G7: =AVERAGE(F7,D7) -> 369.54
B8: Comps | C8: 253.54 | D8: 253.54 | E8: 397.02 | F8: 397.02 | G8: =AVERAGE(F8,D8) -> 325.28 | H8: =MEDIAN(G5:G8) -> 310.7675 | I8: =MEDIAN(G6:G8) -> 325.28 | J8: =MEDIAN(G7:G8) -> 347.41

Sheet Case Comparison
C3: Open | D3: Low | E3: High | F3: Close | H3: Median | I3: Median excl. public market | J3: Median DCF
B4: 52 wk avg (2025) | C4: 116.56 | D4: 116.56 | E4: 281.55 | F4: 281.55 | G4: =AVERAGE(F4,D4) -> 199.055
B5: Blended share price | C5: 134.72 | D5: 134.72 | E5: 457.79 | F5: 457.79 | G5: =AVERAGE(F5,D5) -> 296.255
B6: Perpetuity growth DCF | D6: 74.405444 | E6: 384.37381 | G6: =MEDIAN(D6:E6) -> 229.38963 | L6: =AVERAGE(D6:E6) -> 229.38963
B7: Exit multiple DCF | D7: 222.39459 | E7: 530.02303 | G7: =MEDIAN(D7:E7) -> 376.20881 | L7: =AVERAGE(D7:E7) -> 376.20881 | M7: =AVERAGE(L6:L7) -> 302.79922
B8: Comps | C8: 253.54 | D8: 253.54 | E8: 397.02 | F8: 397.02 | G8: =AVERAGE(F8,D8) -> 325.28 | H8: =MEDIAN(G5:G8) -> 310.7675 | I8: =MEDIAN(G6:G8) -> 325.28 | J8: =MEDIAN(G6:G7) -> 302.79922 | M8: 245
M9: =M7/M8-1 -> 0.23591518
B44: Revenue Growth | C44: 2021A | D44: 2022A | E44: 2023A | F44: 2024A | G44: 2025E | H44: 2026E | I44: 2027E | J44: 2028E
B45: Base Case | C45: 2932.4 | D45: 2619.3 | E45: 3318.6 | F45: 4673.4 | G45: 6309.09 | H45: 8517.2715 | I45: 11498.317 | J45: 15522.727
B46: Bull Case | C46: 2932.4 | D46: 2619.3 | E46: 3318.6 | F46: 4984.96 | G46: 6879.2448 | H46: 8900.023 | I46: 12282.032 | J46: 16949.204
B47: Bear Case | C47: 2932.4 | D47: 2619.3 | E47: 3318.6 | F47: 4206.06 | G47: 5467.878 | H47: 7108.2414 | I47: 9240.7138 | J47: 12012.928
B57: Capex | C57: 2021A | D57: 2022A | E57: 2023A | F57: 2024A | G57: 2025E | H57: 2026E | I57: 2027E | J57: 2028E
B58: Base Case | C58: 540.3 | D58: 903.6 | E58: 1386.3 | F58: 1526 | G58: 1577.2725 | H58: 1533.1089 | I58: 1379.798 | J58: 1244.9227
B59: Bull Case | C59: 540.3 | D59: 903.6 | E59: 1386.3 | F59: 1526 | G59: 1375.849 | H59: 1335.0034 | I59: 1228.2032 | J59: 1359.3261
B60: Bear Case | C60: 540.3 | D60: 903.6 | E60: 1386.3 | F60: 1526 | G60: 1531.0058 | H60: 1421.6483 | I60: 1386.1071 | J60: 963.43682
B70: Tax spent | C70: 2021A | D70: 2022A | E70: 2023A | F70: 2024A | G70: 2025E | H70: 2026E | I70: 2027E | J70: 2028E
B71: Base Case | C71: 103.5 | D71: 52.8 | E71: 60.55 | F71: 114.3 | G71: 757.0908 | H71: 1107.2453 | I71: 1724.7475 | J71: 2483.6364
B72: Bull Case | C72: 103.5 | D72: 52.8 | E72: 60.55 | F72: 114.3 | G72: 825.50938 | H72: 1068.0028 | I72: 1719.4844 | J72: 2542.3806
B73: Bear Case | C73: 103.5 | D73: 52.8 | E73: 60.55 | F73: 114.3 | G73: 492.10902 | H73: 852.98897 | I73: 1663.3285 | J73: 2522.7149

Sheet Formatting
B2: WACC | G2: Total Value | I2: % | J2: Cost
B3: MV of Debt | G3: =WACC!G21/1000000 -> 891.9 | I3: =G3/G5 -> 0.032705633 | J3: =WACC!J11 -> 0.05612979
B4: MV of Equity | G4: =WACC!G22/1000000 -> 26378.632 | I4: =G4/G5 -> 0.96729437 | J4: =WACC!J18 -> 0.121
B5: Total | G5: =SUM(G3:G4) -> 27270.532 | I5: =SUM(I3:I4) -> 1 | J5: =I3*J3+I4*J4 -> 0.11887838

Sheet Stock Data
A1: Date | B1: Price | D1: Open | E1: High | F1: Low | G1: Vol. | H1: Change % | L1: Date | M1: 45962 | N1: 45931 | O1: 45901 | P1: 45870 | Q1: 45839 | R1: 45809 | S1: 45778 | T1: 45748 | U1: 45717 | V1: 45689 | W1: 45658 | X1: 45627 | Y1: 45597 | Z1: 45566 | AA1: 45536 | AB1: 45505 | AC1: 45474 | AD1: 45444 | AE1: 45413 | AF1: 45383 | AG1: 45352 | AH1: 45323 | AI1: 45292 | AJ1: 45261 | AK1: 45231 | AL1: 45200 | AM1: 45170 | AN1: 45139 | AO1: 45108 | AP1: 45078 | AQ1: 45047 | AR1: 45017 | AS1: 44986 | AT1: 44958 | AU1: 44927 | AV1: 44896 | AW1: 44866 | AX1: 44835 | AY1: 44805 | AZ1: 44774 | BA1: 44743 | BB1: 44713 | BC1: 44682 | BD1: 44652 | BE1: 44621 | BF1: 44593 | BG1: 44562 | BH1: 44531 | BI1: 44501 | BJ1: 44470 | BK1: 44440 | BL1: 44409 | BM1: 44378 | BN1: 44348 | BO1: 44317 | BP1: 44287 | BQ1: 44256 | BR1: 44228 | BS1: 44197
A2: 45962 | B2: 245.84 | D2: 266.23 | E2: 281.5 | F2: 244.01 | G2: 31.57M | H2: -0.079 | L2: Price | M2: 245.84 | N2: 266.94 | O2: 220.53 | P2: 195.19 | Q2: 174.73 | R2: 165.54 | S2: 158.08 | T2: 125.82 | U2: 126.43 | V2: 136.18 | W2: 167.52 | X2: 176.24 | Y2: 199.27 | Z2: 194.48 | AA2: 249.44 | AB2: 227.37 | AC2: 215.99 | AD2: 225.46 | AE2: 271.76 | AF2: 176.3 | AG2: 168.8 | AH2: 153.89 | AI2: 146.3 | AJ2: 172.28 | AK2: 157.78 | AL2: 142.45 | AM2: 161.59 | AN2: 189.12 | AO2: 207.4 | AP2: 190.09 | AQ2: 202.96 | AR2: 182.58 | AS2: 217.5 | AT2: 169.14 | AU2: 177.6 | AV2: 149.79 | AW2: 172.53 | AX2: 145.57 | AY2: 132.27 | AZ2: 127.55 | BA2: 99.17 | BB2: 68.13 | BC2: 70.61 | BD2: 73.03 | BE2: 83.74 | BF2: 75.29 | BG2: 78.38 | BH2: 87.16 | BI2: 103.6 | BJ2: 119.59 | BK2: 95.46 | BL2: 94 | BM2: 86.04 | BN2: 90.51 | BO2: 76.11 | BP2: 76.53 | BQ2: 87.3 | BR2: 81.02 | BS2: 99.15
A3: 45931 | B3: 266.94 | D3: 221.78 | E3: 269.67 | F3: 216.63 | G3: 54.60M | H3: 0.2104
A4: 45901 | B4: 220.53 | D4: 190.15 | E4: 228.34 | F4: 187.64 | G4: 46.31M | H4: 0.1298
A5: 45870 | B5: 195.19 | D5: 186.34 | E5: 221.5 | F5: 176.47 | G5: 72.34M | H5: 0.1171
A6: 45839 | B6: 174.73 | D6: 165.02 | E6: 189.5 | F6: 158.81 | G6: 71.99M | H6: 0.0555
A7: 45809 | B7: 165.54 | D7: 158.21 | E7: 179.5 | F7: 135.5 | G7: 100.17M | H7: 0.0472
A8: 45778 | B8: 158.08 | D8: 127.94 | E8: 198.87 | F8: 122.47 | G8: 125.26M | H8: 0.2564
A9: 45748 | B9: 125.82 | D9: 126.11 | E9: 144.63 | F9: 116.56 | G9: 92.24M | H9: -0.0048
A10: 45717 | B10: 126.43 | D10: 135.28 | E10: 140.98 | F10: 120.6 | G10: 65.85M | H10: -0.0716
A11: 45689 | B11: 136.18 | D11: 163.31 | E11: 171.54 | F11: 133.9 | G11: 55.30M | H11: -0.1871
A12: 45658 | B12: 167.52 | D12: 177.91 | E12: 201.2 | F12: 158.08 | G12: 46.46M | H12: -0.0495
A13: 45627 | B13: 176.24 | D13: 204.35 | E13: 212.15 | F13: 173.36 | G13: 40.80M | H13: -0.1156
A14: 45597 | B14: 199.27 | D14: 195.85 | E14: 221.2 | F14: 173.37 | G14: 71.09M | H14: 0.0246
... A107: 42767 | B107: 36.19 | D107: 31.4 | E107: 38.5 | F107: 30.8 | G107: 62.06M | H107: 0.1603
